swift_bench-2.0.0.data/scripts/swift-bench
swift_bench-2.0.0.data/scripts/swift-bench-client
swiftbench/__init__.py
swiftbench/bench.py
swiftbench/utils.py
swiftbench/cli/__init__.py
tests/__init__.py
tests/test_bench.py
tests/test_cli.py
tests/test_utils.py
swift_bench-2.0.0.dist-info/AUTHORS
swift_bench-2.0.0.dist-info/LICENSE
swift_bench-2.0.0.dist-info/METADATA
swift_bench-2.0.0.dist-info/WHEEL
swift_bench-2.0.0.dist-info/top_level.txt
swift_bench-2.0.0.dist-info/RECORD
